colonyscanalyser/base.py
colonyscanalyser/colony.py
colonyscanalyser/config.py
colonyscanalyser/file_access.py
colonyscanalyser/geometry.py
colonyscanalyser/growth_curve.py
colonyscanalyser/image_file.py
colonyscanalyser/imaging.py
colonyscanalyser/main.py
colonyscanalyser/plate.py
colonyscanalyser/plots.py
colonyscanalyser/plotting.py
colonyscanalyser/utilities.py
colonyscanalyser/align/strategy.py
colonyscanalyser/align/transform.py
colonyscanalyser-0.6.2.dist-info/LICENSE
colonyscanalyser-0.6.2.dist-info/METADATA
colonyscanalyser-0.6.2.dist-info/WHEEL
colonyscanalyser-0.6.2.dist-info/entry_points.txt
colonyscanalyser-0.6.2.dist-info/top_level.txt
colonyscanalyser-0.6.2.dist-info/RECORD
