Metadata-Version: 2.1
Name: colonyscanalyser
Version: 0.6.2
Summary: An image analysis tool for measuring microorganism colony growth
Home-page: https://github.com/Erik-White/ColonyScanalyser/
Author: Erik White
Author-email: 
License: GPL-3.0
Platform: UNKNOWN
Requires-Python: >=3.7
Requires-Dist: numpy (>=1.18)
Requires-Dist: matplotlib
Requires-Dist: scikit-image (>=0.17)
Requires-Dist: imreg-dft
Requires-Dist: webcolors
Requires-Dist: importlib-metadata (~=1.0) ; python_version < "3.8"
Provides-Extra: dev
Requires-Dist: flake8 ; extra == 'dev'
Requires-Dist: check-manifest ; extra == 'dev'
Requires-Dist: pytest ; extra == 'dev'
Requires-Dist: pytest-cov ; extra == 'dev'
Provides-Extra: test
Requires-Dist: flake8 ; extra == 'test'
Requires-Dist: pytest ; extra == 'test'
Requires-Dist: pytest-cov ; extra == 'test'
